app_creator/__init__.py
app_creator/cli.py
migrations/__init__.py
models/__init__.py
parfaite/__init__.py
parfaite/admin.py
parfaite/apps.py
parfaite/tests.py
parfaite/urls.py
parfaite/migrations/__init__.py
parfaite/models/__init__.py
parfaite/views/__init__.py
tr/__init__.py
tr/admin.py
tr/apps.py
tr/tests.py
tr/urls.py
tr/migrations/__init__.py
tr/models/__init__.py
tr/views/__init__.py
views/__init__.py
django_app_parfaite-0.7.0.dist-info/METADATA
django_app_parfaite-0.7.0.dist-info/WHEEL
django_app_parfaite-0.7.0.dist-info/entry_points.txt
django_app_parfaite-0.7.0.dist-info/top_level.txt
django_app_parfaite-0.7.0.dist-info/RECORD
