Metadata-Version: 2.4
Name: django-app-Parfaite
Version: 0.7.0
Summary: Générateur de structure d'app Django personnalisée
Author: ParfaiteSekongo
Author-email: p88971582@gmail.com
License: MIT
Classifier: Programming Language :: Python :: 3
Classifier: Framework :: Django
Classifier: License :: OSI Approved :: MIT License
Dynamic: author
Dynamic: author-email
Dynamic: classifier
Dynamic: description
Dynamic: description-content-type
Dynamic: license
Dynamic: summary
